bincrafters_conventions/__init__.py
bincrafters_conventions/bincrafters_conventions.py
bincrafters_conventions/main.py
bincrafters_conventions/requirements.txt
bincrafters_conventions/requirements_test.txt
bincrafters_conventions/actions/__init__.py
bincrafters_conventions/actions/check_for_deprecated_generators.py
bincrafters_conventions/actions/check_for_deprecated_methods.py
bincrafters_conventions/actions/check_for_deprecated_settings.py
bincrafters_conventions/actions/check_for_download_hash.py
bincrafters_conventions/actions/check_for_license.py
bincrafters_conventions/actions/check_for_required_attributes.py
bincrafters_conventions/actions/travis_1_expected.yml
bincrafters_conventions/actions/travis_1_expected_gha.yml
bincrafters_conventions/actions/travis_2_expected.yml
bincrafters_conventions/actions/travis_2_expected_gha.yml
bincrafters_conventions/actions/travis_3_expected.yml
bincrafters_conventions/actions/update_a_jobs.py
bincrafters_conventions/actions/update_a_path_manipulation.py
bincrafters_conventions/actions/update_a_python_environment_variable.py
bincrafters_conventions/actions/update_a_python_version.py
bincrafters_conventions/actions/update_a_use_package_tools_auto.py
bincrafters_conventions/actions/update_c_H046_no_verbose_cmake_file.py
bincrafters_conventions/actions/update_c_attributes.py
bincrafters_conventions/actions/update_c_default_options_to_dict.py
bincrafters_conventions/actions/update_c_delete_meta_lines.py
bincrafters_conventions/actions/update_c_deprecated_attributes.py
bincrafters_conventions/actions/update_c_imports.py
bincrafters_conventions/actions/update_c_minimum_cmake_version_required.py
bincrafters_conventions/actions/update_c_openssl_version_patch.py
bincrafters_conventions/actions/update_c_recipe_references.py
bincrafters_conventions/actions/update_c_recipe_references_manual.yml
bincrafters_conventions/actions/update_c_recipe_references_manual_names.yml
bincrafters_conventions/actions/update_c_remove_compiler_cppstd.py
bincrafters_conventions-1.2.1.dist-info/LICENSE.md
bincrafters_conventions-1.2.1.dist-info/METADATA
bincrafters_conventions-1.2.1.dist-info/WHEEL
bincrafters_conventions-1.2.1.dist-info/entry_points.txt
bincrafters_conventions-1.2.1.dist-info/top_level.txt
bincrafters_conventions-1.2.1.dist-info/RECORD
