Metadata-Version: 2.1
Name: bincrafters_conventions
Version: 1.2.1
Summary: Bincrafters script to apply Conan conventions and update CI jobs
Home-page: https://github.com/bincrafters/bincrafters-conventions
Author: Bincrafters
Author-email: bincrafters@gmail.com
License: MIT
Keywords: conan,C/C++,package,libraries,developer,manager,dependency,tool,c,c++,cpp,convention,updates
Classifier: Development Status :: 5 - Production/Stable
Classifier: Intended Audience :: Developers
Classifier: Topic :: Software Development :: Build Tools
Classifier: License :: OSI Approved :: MIT License
Classifier: Programming Language :: Python :: 3
License-File: LICENSE.md
Requires-Dist: requests >=2.22.0
Requires-Dist: GitPython >=3.0.4
Requires-Dist: conan <2.0.0,>=1.53.0
Provides-Extra: test
Requires-Dist: pytest >=5.2.2 ; extra == 'test'
Requires-Dist: pytest-cov >=2.8.1 ; extra == 'test'
Requires-Dist: codecov >=2.1.10 ; extra == 'test'
